dbaas_foreman/__init__.py
dbaas_foreman/dbaas_api.py
dbaas_foreman/exceptions.py
dbaas_foreman/foreman_provider.py
dbaas_foreman-0.1.9.dist-info/LICENSE
dbaas_foreman-0.1.9.dist-info/METADATA
dbaas_foreman-0.1.9.dist-info/WHEEL
dbaas_foreman-0.1.9.dist-info/top_level.txt
dbaas_foreman-0.1.9.dist-info/RECORD
