Metadata-Version: 2.1
Name: dbaas-foreman
Version: 0.1.9
Summary: DBaaS Foreman is a simple foreman api wrapper for DBaaS
Home-page: https://github.com/felippemr/dbaas_foreman
Author: Felippe da Motta Raposo
Author-email: raposo.felippe@gmail.com
License: MIT license
Keywords: dbaas_foreman
Platform: UNKNOWN
Classifier: Development Status :: 2 - Pre-Alpha
Classifier: Intended Audience :: Developers
Classifier: License :: OSI Approved :: MIT License
Classifier: Natural Language :: English
Classifier: Programming Language :: Python :: 2
Classifier: Programming Language :: Python :: 2.6
Classifier: Programming Language :: Python :: 2.7
Classifier: Programming Language :: Python :: 3
Classifier: Programming Language :: Python :: 3.3
Classifier: Programming Language :: Python :: 3.4
Classifier: Programming Language :: Python :: 3.5
Requires-Dist: pbr (==1.10.0)
Requires-Dist: python-foreman (==0.4.5)
Requires-Dist: requests (==2.10.0)
Requires-Dist: six (==1.10.0)
